autoexif/__init__.py
autoexif/cli.py
autoexif/exiftool.py
autoexif/operations.py
autoexif/utils.py
autoexif/resources/exiftool.exe
autoexif/resources/exiftool_files.zip
autoexif/resources/icon.png
autoexif-1.0.2.data/data/scripts/init_exiftool.py
autoexif-1.0.2.data/data/scripts/install_exiftool.py
autoexif-1.0.2.dist-info/licenses/LICENSE
autoexif-1.0.2.dist-info/METADATA
autoexif-1.0.2.dist-info/WHEEL
autoexif-1.0.2.dist-info/entry_points.txt
autoexif-1.0.2.dist-info/top_level.txt
autoexif-1.0.2.dist-info/RECORD
