Metadata-Version: 2.4
Name: autoexif
Version: 1.0.2
Summary: CLI tool for easy metadata extraction and manipulation
Home-page: https://github.com/SirCryptic/autoexif
Author: SirCryptic
Author-email: sircryptic@protonmail.com
License: MIT
Classifier: Programming Language :: Python :: 3
Classifier: Operating System :: Microsoft :: Windows
Classifier: Operating System :: POSIX :: Linux
Requires-Python: >=3.11
License-File: LICENSE
Requires-Dist: click>=8.1.0
Requires-Dist: requests>=2.28.0
Requires-Dist: prompt_toolkit>=3.0.0
Dynamic: author
Dynamic: author-email
Dynamic: classifier
Dynamic: description
Dynamic: description-content-type
Dynamic: home-page
Dynamic: license
Dynamic: license-file
Dynamic: requires-dist
Dynamic: requires-python
Dynamic: summary
